benchmark/compare_werkzeug.py
docs/gen_ref_nav.py
examples/asgi_minimal.py
examples/simple_app.py
examples/starlette_comparison.py
examples/tokamak_app.py
tests/conftest.py
tests/radix_tree/test_node.py
tests/radix_tree/test_properties.py
tests/radix_tree/test_tree.py
tests/radix_tree/test_utils.py
tests/web/test_methods.py
tests/web/test_router.py
tokamak/__init__.py
tokamak/methods.py
tokamak/router.py
tokamak/radix_tree/__init__.py
tokamak/radix_tree/node.py
tokamak/radix_tree/tree.py
tokamak/radix_tree/utils.py
tokamak/web/__init__.py
tokamak/web/app.py
tokamak/web/errors.py
tokamak/web/request.py
tokamak/web/response.py
tokamak-0.6.1.dist-info/LICENSE
tokamak-0.6.1.dist-info/METADATA
tokamak-0.6.1.dist-info/WHEEL
tokamak-0.6.1.dist-info/top_level.txt
tokamak-0.6.1.dist-info/RECORD
