Metadata-Version: 2.1
Name: tokamak
Version: 0.6.1
Summary: HTTP Router based on radix trees
Author-email: Erik Aker <eraker@gmail.com>
License: MPL-2.0
Project-URL: homepage, https://github.com/erewok/tokamak
Project-URL: repository, https://github.com/erewok/tokamak
Project-URL: documentation, https://tokamak.readthedocs.io/en/latest/
Classifier: Development Status :: 3 - Alpha
Classifier: Environment :: Web Environment
Classifier: Intended Audience :: Developers
Classifier: License :: OSI Approved :: Mozilla Public License 2.0 (MPL 2.0)
Classifier: Operating System :: OS Independent
Classifier: Programming Language :: Python
Classifier: Programming Language :: Python :: 3
Classifier: Programming Language :: Python :: 3.11
Classifier: Programming Language :: Python :: 3.12
Classifier: Topic :: Internet :: WWW/HTTP :: Dynamic Content
Classifier: Topic :: Software Development :: Libraries :: Python Modules
Requires-Python: >=3.11
License-File: LICENSE
Provides-Extra: benchmarks
Requires-Dist: Werkzeug ; extra == 'benchmarks'
Provides-Extra: docs
Requires-Dist: mkdocs >=1.6.1 ; extra == 'docs'
Requires-Dist: mkdocstrings[python] >=0.27.0 ; extra == 'docs'
Requires-Dist: mkdocs-coverage >=1.1.0 ; extra == 'docs'
Requires-Dist: markdown-callouts >=0.4.0 ; extra == 'docs'
Requires-Dist: markdown-exec >=1.9.3 ; extra == 'docs'
Requires-Dist: mkdocs-gen-files >=0.5.0 ; extra == 'docs'
Requires-Dist: mkdocs-literate-nav >=0.6.1 ; extra == 'docs'
Requires-Dist: mkdocs-material >=9.5.44 ; extra == 'docs'
Requires-Dist: mkdocs-section-index >=0.3.9 ; extra == 'docs'
Provides-Extra: examples
Requires-Dist: starlette ; extra == 'examples'
Requires-Dist: hypercorn ; extra == 'examples'
Requires-Dist: trio ; extra == 'examples'
Provides-Extra: web
Requires-Dist: trio ; extra == 'web'
